botnikkk/__init__.py
botnikkk/formatting.py
botnikkk-0.1.3.dist-info/LICENSE
botnikkk-0.1.3.dist-info/METADATA
botnikkk-0.1.3.dist-info/WHEEL
botnikkk-0.1.3.dist-info/top_level.txt
botnikkk-0.1.3.dist-info/RECORD
